codac4matlab/__init__.py
codac4matlab/_core.cpython-39-x86_64-linux-gnu.so
codac4matlab/_graphics.cpython-39-x86_64-linux-gnu.so
codac4matlab/_unsupported.cpython-39-x86_64-linux-gnu.so
codac4matlab/empty.cpython-39-x86_64-linux-gnu.so
codac4matlab/version.py
codac4matlab/core/__init__.py
codac4matlab/graphics/__init__.py
codac4matlab/tests/__init__.py
codac4matlab/tests/test_AnalyticFunction.py
codac4matlab/tests/test_AnalyticTraj.py
codac4matlab/tests/test_Approx.py
codac4matlab/tests/test_BoolInterval.py
codac4matlab/tests/test_Color.py
codac4matlab/tests/test_ConvexPolygon.py
codac4matlab/tests/test_CtcAction.py
codac4matlab/tests/test_CtcCartProd.py
codac4matlab/tests/test_CtcCtcBoundary.py
codac4matlab/tests/test_CtcFixpoint.py
codac4matlab/tests/test_CtcInter.py
codac4matlab/tests/test_CtcInverse.py
codac4matlab/tests/test_CtcInverseNotIn.py
codac4matlab/tests/test_CtcLazy.py
codac4matlab/tests/test_CtcPolygon.py
codac4matlab/tests/test_CtcSegment.py
codac4matlab/tests/test_Ellipsoid.py
codac4matlab/tests/test_IntFullPivLU.py
codac4matlab/tests/test_Interval.py
codac4matlab/tests/test_IntervalMatrix.py
codac4matlab/tests/test_IntervalVector.py
codac4matlab/tests/test_Interval_operations.py
codac4matlab/tests/test_Matrix.py
codac4matlab/tests/test_OctaSym.py
codac4matlab/tests/test_Polygon.py
codac4matlab/tests/test_SampledTraj.py
codac4matlab/tests/test_Segment.py
codac4matlab/tests/test_SepCartProd.py
codac4matlab/tests/test_SepCtcBoundary.py
codac4matlab/tests/test_SepInverse.py
codac4matlab/tests/test_SepPolygon.py
codac4matlab/tests/test_SepProj.py
codac4matlab/tests/test_SepTransform.py
codac4matlab/tests/test_SlicedTube.py
codac4matlab/tests/test_SlicedTube_integral.py
codac4matlab/tests/test_TDomain.py
codac4matlab/tests/test_Vector.py
codac4matlab/tests/test_arithmetic_add.py
codac4matlab/tests/test_arithmetic_div.py
codac4matlab/tests/test_arithmetic_mul.py
codac4matlab/tests/test_arithmetic_sub.py
codac4matlab-2.0.0.dev20.dist-info/METADATA
codac4matlab-2.0.0.dev20.dist-info/WHEEL
codac4matlab-2.0.0.dev20.dist-info/top_level.txt
codac4matlab-2.0.0.dev20.dist-info/RECORD
